{"dependencies":[{"name":"E:\\项目\\react\\postcss.config.js","includedInParent":true,"mtime":1513393531037},{"name":"_css_loader"}],"generated":{"css":".ant-table-thead > tr > th, .ant-table-tbody > tr > td {\n  padding: 10px; }\n\n.table-img {\n  max-width: 100px;\n  max-height: 35px;\n  -o-object-fit: cover;\n     object-fit: cover;\n  margin-right: 4px;\n  border-radius: 4px; }\n\n.small-img {\n  max-width: 50px;\n  max-height: 30px;\n  margin-right: 4px;\n  border-radius: 4px; }\n\n.table-img-big {\n  max-width: 350px;\n  max-height: 350px;\n  border-radius: 4px; }\n\n.ant-table-tbody .ant-table-row {\n  height: 56px; }\n","js":"\n        var reloadCSS = require('_css_loader');\n        module.hot.dispose(reloadCSS);\n        module.hot.accept(reloadCSS);\n      "},"hash":"b3a13e14a5fe76f8de2bce3dacb0b98f","cacheData":{}}