{"dependencies":[{"name":"E:\\项目\\react\\package.json","includedInParent":true,"mtime":1521429741467},{"name":"E:\\项目\\react\\.babelrc","includedInParent":true,"mtime":1513393531020},{"name":"E:\\项目\\react\\node_modules\\babel-polyfill\\node_modules\\core-js\\package.json","includedInParent":true,"mtime":1513393692170}],"generated":{"js":"var core = module.exports = { version: '2.5.3' };\nif (typeof __e == 'number') __e = core; // eslint-disable-line no-undef\n","map":{"mappings":[{"source":"..\\node_modules\\babel-polyfill\\node_modules\\core-js\\modules\\_core.js","original":{"line":1,"column":0},"generated":{"line":1,"column":0}},{"source":"..\\node_modules\\babel-polyfill\\node_modules\\core-js\\modules\\_core.js","original":{"line":2,"column":0},"generated":{"line":2,"column":0}},{"source":"..\\node_modules\\babel-polyfill\\node_modules\\core-js\\modules\\_core.js","original":{"line":3,"column":0},"generated":{"line":3,"column":0}}],"sources":{"..\\node_modules\\babel-polyfill\\node_modules\\core-js\\modules\\_core.js":"var core = module.exports = { version: '2.5.3' };\nif (typeof __e == 'number') __e = core; // eslint-disable-line no-undef\n"},"lineCount":3}},"hash":"624b212f67be7cf911e313371c44220e","cacheData":{"env":{}}}